{
  "date": "2026-04-30",
  "total_sent": 320,
  "total_pool": 72245,
  "candidates": [
    {
      "id": "4213",
      "name": "hiimjhona",
      "country": "Unknown",
      "flag": "\ud83c\udf0d",
      "score": 8.0,
      "contacts": {
        "email": "johncamacho0175@gmail.com",
        "discord": "Jhona#8870"
      },
      "badge": "gold",
      "verified": false,
      "hireMe": true,
      "ytChannel": null,
      "ytjobsUrl": "https://ytjobs.co/talent/profile/4213"
    },
    {
      "id": "27434",
      "name": "Anton Byarts",
      "country": "Unknown",
      "flag": "\ud83c\udf0d",
      "score": 8.0,
      "contacts": {
        "email": "antonbyarts@hotmail.com",
        "discord": "byarts",
        "website": "byarts.se"
      },
      "badge": "silver",
      "verified": false,
      "hireMe": true,
      "ytChannel": {
        "name": "Anton ByArts",
        "subscribers": 3,
        "abvSubs": "3"
      },
      "ytjobsUrl": "https://ytjobs.co/talent/profile/27434"
    },
    {
      "id": "2401",
      "name": "Mihail Dimovski",
      "country": "Unknown",
      "flag": "\ud83c\udf0d",
      "score": 8.0,
      "contacts": {
        "email": "dimovski.media@gmail.com",
        "discord": "miksach",
        "twitter": "miksach"
      },
      "badge": "silver",
      "verified": false,
      "hireMe": true,
      "ytChannel": {
        "name": "Miksach",
        "subscribers": 2,
        "abvSubs": "2"
      },
      "ytjobsUrl": "https://ytjobs.co/talent/profile/2401"
    },
    {
      "id": "45614",
      "name": "Ali Mostafa",
      "country": "Unknown",
      "flag": "\ud83c\udf0d",
      "score": 8.0,
      "contacts": {
        "email": "alii.videoeditor@gmail.com",
        "discord": "alimostafa54"
      },
      "badge": "silver",
      "verified": false,
      "hireMe": true,
      "ytChannel": {
        "name": "Ali Mostafa54",
        "subscribers": 81,
        "abvSubs": "81"
      },
      "ytjobsUrl": "https://ytjobs.co/talent/profile/45614"
    },
    {
      "id": "34203",
      "name": "Cu3tom",
      "country": "Unknown",
      "flag": "\ud83c\udf0d",
      "score": 8.0,
      "contacts": {
        "email": "Cu3tomm@gmail.com",
        "discord": "Cu3tom"
      },
      "badge": "silver",
      "verified": false,
      "hireMe": true,
      "ytChannel": {
        "name": "cu3tom",
        "subscribers": 1510,
        "abvSubs": "1.51K"
      },
      "ytjobsUrl": "https://ytjobs.co/talent/profile/34203"
    },
    {
      "id": "283892",
      "name": "Darkness King",
      "country": "Unknown",
      "flag": "\ud83c\udf0d",
      "score": 8.0,
      "contacts": {
        "email": "iheb.cry443@gmail.com",
        "discord": "darkness_king443"
      },
      "badge": "silver",
      "verified": false,
      "hireMe": true,
      "ytChannel": {
        "name": "darkness king",
        "subscribers": 107,
        "abvSubs": "107"
      },
      "ytjobsUrl": "https://ytjobs.co/talent/profile/283892"
    },
    {
      "id": "266788",
      "name": "Ahmed",
      "country": "Unknown",
      "flag": "\ud83c\udf0d",
      "score": 8.0,
      "contacts": {
        "email": "ahmexd.psd@gmail.com",
        "discord": "ahmexd"
      },
      "badge": "simpleVerified",
      "verified": false,
      "hireMe": true,
      "ytChannel": {
        "name": "Ahmexd",
        "subscribers": 380,
        "abvSubs": "380"
      },
      "ytjobsUrl": "https://ytjobs.co/talent/profile/266788"
    },
    {
      "id": "23788",
      "name": "George Wilkins",
      "country": "Unknown",
      "flag": "\ud83c\udf0d",
      "score": 8.0,
      "contacts": {
        "email": "georgewilkins_@outlook.com",
        "discord": "gwilkins"
      },
      "badge": "simpleVerified",
      "verified": false,
      "hireMe": true,
      "ytChannel": {
        "name": "Geog Wilkins \u2661",
        "subscribers": 248,
        "abvSubs": "248"
      },
      "ytjobsUrl": "https://ytjobs.co/talent/profile/23788"
    },
    {
      "id": "277851",
      "name": "I'm Eric",
      "country": "Unknown",
      "flag": "\ud83c\udf0d",
      "score": 8.0,
      "contacts": {
        "email": "onlyeric878@gmail.com",
        "discord": "eric878"
      },
      "badge": "silver",
      "verified": false,
      "hireMe": true,
      "ytChannel": {
        "name": "ASTONISH - PUBGM",
        "subscribers": 253,
        "abvSubs": "253"
      },
      "ytjobsUrl": "https://ytjobs.co/talent/profile/277851"
    },
    {
      "id": "415469",
      "name": "Robert Menezes",
      "country": "Unknown",
      "flag": "\ud83c\udf0d",
      "score": 8.0,
      "contacts": {
        "email": "robertsouza915@gmail.com",
        "discord": "r0b314"
      },
      "badge": "simpleVerified",
      "verified": false,
      "hireMe": true,
      "ytChannel": {
        "name": "Robert Menezes | Video Editor",
        "subscribers": 37,
        "abvSubs": "37"
      },
      "ytjobsUrl": "https://ytjobs.co/talent/profile/415469"
    }
  ],
  "generated_at": "2026-04-30T13:01:04.154851Z"
}